.gitignore
.mrconfig
.travis.yml
LICENSE
README.md
plpydbapi.py
setup.py
plpydbapi.egg-info/PKG-INFO
plpydbapi.egg-info/SOURCES.txt
plpydbapi.egg-info/dependency_links.txt
plpydbapi.egg-info/top_level.txt
test/__init__.py
test/plpy_test_runner.py
test/run_test_plpydbapi_dbapi20.sql
test/test_plpydbapi_dbapi20.py