Metadata-Version: 1.1
Name: plpydbapi
Version: 0.20121018
Summary: DB-API compatible interface on top of PL/Python
Home-page: https://github.com/petere/plpydbapi
Author: Peter Eisentraut
Author-email: peter@eisentraut.org
License: UNKNOWN
Platform: UNKNOWN
Classifier: Development Status :: 4 - Beta
Classifier: Environment :: Plugins
Classifier: License :: OSI Approved :: MIT License
Classifier: Programming Language :: Python
Classifier: Programming Language :: Python :: 2
Classifier: Programming Language :: Python :: 3
Classifier: Topic :: Database
Classifier: Topic :: Software Development :: Libraries :: Python Modules
